{"inkVersion":21,"root":[[{"->":"start"},["done",{"#f":5,"#n":"g-0"}],null],"done",{"start":[["^Good morning! Georgie, is it?","\n","ev","str","^Yeah, good morning! What can I get for you?","/str","/ev",{"*":".^.c-0","flg":20},"ev","str","^Yep! Eric, right?","/str","/ev",{"*":".^.c-1","flg":20},{"c-0":["\n","^Just a ","ev",{"VAR?":"coffee"},"out","/ev","^, please!","\n",{"->":".^.^.g-0"},{"#f":5}],"c-1":["\n","^You got it! Good to see you. Can I get some ","ev",{"VAR?":"coffee"},"out","/ev","\n","ev",{"VAR?":"affection"},1,"+",{"VAR=":"affection","re":true},"/ev",{"->":".^.^.g-0"},{"#f":5}],"g-0":["^How's business going? I remember you said that you run this place yourself.","\n","ev","str","^Pretty good! It can get kind of overwhelming but this is my passion.","/str","/ev",{"*":".^.c-2","flg":20},"ev","str","^Not too bad!","/str","/ev",{"*":".^.c-3","flg":20},{"c-2":["\n","^That makes sense. If you're passionate about something it can make the work worth it!","\n","ev",{"VAR?":"affection"},1,"+",{"VAR=":"affection","re":true},"/ev",{"->":".^.^.^.g-1"},{"#f":5}],"c-3":["\n","^Good to hear.","\n",{"->":".^.^.^.g-1"},{"#f":5}],"#f":5}],"g-1":["^Did you go to school for anything or did you know you were gonna open a cafe?","\n","ev","str","^I went to university but it wasn't a great time.","/str","/ev",{"*":".^.c-4","flg":20},"ev","str","^Both! I went to school for business since I knew I would have to be pretty business-savvy.","/str","/ev",{"*":".^.c-5","flg":20},{"c-4":["\n","^Damn, sorry to hear that. At least you found success after!","\n",{"->":".^.^.^.g-2"},{"#f":5}],"c-5":["\n","^That's so cool...you know how to run all the different aspects of a cafe.","\n","ev",{"VAR?":"affection"},1,"+",{"VAR=":"affection","re":true},"/ev",{"->":".^.^.^.g-2"},{"#f":5}],"#f":5}],"g-2":["^I'm actually in business school right now...alongside my internship. Unpaid, of course.","\n","ev","str","^That's rough-- hopefully you're getting really good experience since it's unpaid.","/str","/ev",{"*":".^.c-6","flg":20},"ev","str","^That sounds like a lot.","/str","/ev",{"*":".^.c-7","flg":20},{"c-6":["\n","^It's alright...I just wish I could work a regular job already. Interning sucks.","\n","ev",{"VAR?":"affection"},1,"+",{"VAR=":"affection","re":true},"/ev",{"->":".^.^.^.g-3"},{"#f":5}],"c-7":["\n","^Yup.","\n",{"->":".^.^.^.g-3"},{"#f":5}],"#f":5}],"g-3":["^Thanks for the coffee. It really helps keep me to get through my internship days.","\n","ev","str","^I'm happy it can help! You're working super hard, good luck with everything!","/str","/ev",{"*":".^.c-8","flg":20},"ev","str","^Have a good day!","/str","/ev",{"*":".^.c-9","flg":20},{"c-8":["\n","^Thanks, Georgie-- you too!","\n","ev",{"VAR?":"affection"},1,"+",{"VAR=":"affection","re":true},"/ev",{"->":".^.^.^.g-4"},{"#f":5}],"c-9":["\n","^Thank you!","\n",{"->":".^.^.^.g-4"},{"#f":5}],"#f":5}],"g-4":["end",{"#f":5}]}],{"#f":1}],"global decl":["ev",0,{"VAR=":"affection"},"str","^Eric","/str",{"VAR=":"name"},"str","^","/str",{"VAR=":"coffee"},"/ev","end",null],"#f":1}],"listDefs":{}}